flaskerk/__init__.py
flaskerk/base.py
flaskerk/config.py
flaskerk/converters.py
flaskerk/exception.py
flaskerk/utils.py
flaskerk/view.py
flaskerk/templates/redoc.html
flaskerk/templates/swagger.html
flaskerk-0.6.3.dist-info/METADATA
flaskerk-0.6.3.dist-info/RECORD
flaskerk-0.6.3.dist-info/WHEEL
flaskerk-0.6.3.dist-info/entry_points.txt
flaskerk-0.6.3.dist-info/top_level.txt
