Metadata-Version: 2.1
Name: flaskerk
Version: 0.6.3
Summary: UNKNOWN
Home-page: https://github.com/kemingy/flaskerk
Author: Keming Yang
Author-email: kemingy94@gmail.com
License: UNKNOWN
Platform: UNKNOWN
Classifier: Programming Language :: Python :: 3
Requires-Dist: flask (>=1.0)
Requires-Dist: pydantic (>=1.2)
